corebrum/__init__.py
corebrum/client.py
corebrum/exceptions.py
corebrum/utils.py
corebrum-0.1.1.dist-info/licenses/LICENSE
tests/__init__.py
tests/conftest.py
tests/test_corebrum.py
corebrum-0.1.1.dist-info/METADATA
corebrum-0.1.1.dist-info/WHEEL
corebrum-0.1.1.dist-info/top_level.txt
corebrum-0.1.1.dist-info/RECORD
