Metadata-Version: 2.4
Name: corebrum
Version: 0.1.1
Summary: Execute Python code transparently on Corebrum distributed compute infrastructure
Home-page: https://github.com/Corebrum/corebrum-pip
Author: Corebrum
Author-email: Corebrum <hello@corebrum.com>
License-Expression: MIT
Project-URL: Homepage, https://github.com/Corebrum/corebrum-pip
Project-URL: Documentation, https://github.com/Corebrum/corebrum-pip#readme
Project-URL: Repository, https://github.com/Corebrum/corebrum-pip
Project-URL: Bug Reports, https://github.com/Corebrum/corebrum-pip/issues
Keywords: corebrum,distributed,computing,mesh,python,decorator
Classifier: Development Status :: 4 - Beta
Classifier: Intended Audience :: Developers
Classifier: Operating System :: OS Independent
Classifier: Programming Language :: Python :: 3
Classifier: Programming Language :: Python :: 3.7
Classifier: Programming Language :: Python :: 3.8
Classifier: Programming Language :: Python :: 3.9
Classifier: Programming Language :: Python :: 3.10
Classifier: Programming Language :: Python :: 3.11
Classifier: Programming Language :: Python :: 3.12
Classifier: Topic :: Software Development :: Libraries :: Python Modules
Classifier: Topic :: System :: Distributed Computing
Requires-Python: >=3.7
License-File: LICENSE
Requires-Dist: requests>=2.28.0
Requires-Dist: urllib3>=1.26.0
Provides-Extra: dev
Requires-Dist: pytest>=7.0.0; extra == "dev"
Requires-Dist: pytest-cov>=4.0.0; extra == "dev"
Requires-Dist: black>=22.0.0; extra == "dev"
Requires-Dist: flake8>=5.0.0; extra == "dev"
Requires-Dist: mypy>=0.991; extra == "dev"
Dynamic: author
Dynamic: home-page
Dynamic: license-file
Dynamic: requires-python
